setup.cfg
setup.py
flake8_truveris/__init__.py
flake8_truveris/check_truveris.py
flake8_truveris/format_truveris.py
flake8_truveris/inline_comments.py
flake8_truveris/token.py
flake8_truveris/trailing_commas.py
flake8_truveris.egg-info/PKG-INFO
flake8_truveris.egg-info/SOURCES.txt
flake8_truveris.egg-info/dependency_links.txt
flake8_truveris.egg-info/entry_points.txt
flake8_truveris.egg-info/requires.txt
flake8_truveris.egg-info/top_level.txt