Metadata-Version: 1.1
Name: flake8-truveris
Version: 0.3.4
Summary: Flake8 extension for checking Python code against Truveris's code style guide
Home-page: http://github.com/truveris/flake8-truveris
Author: Truveris Inc.
Author-email: engineering@truveris.com
License: MIT
Download-URL: https://github.com/truveris/flake8-truveris/tarball/0.3.4
Platform: UNKNOWN
Classifier: Framework :: Flake8
